CHANGES.txt
LICENSE.txt
MANIFEST.in
README.rst
setup.py
ticktock.py
docs/.DS_Store
docs/Makefile
docs/api.rst
docs/conf.py
docs/index.rst
docs/installation.rst
docs/make.bat
docs/quickstart.rst
test/test_ticktock.py
ticktock.egg-info/.DS_Store
ticktock.egg-info/PKG-INFO
ticktock.egg-info/SOURCES.txt
ticktock.egg-info/dependency_links.txt
ticktock.egg-info/top_level.txt