Metadata-Version: 1.1
Name: ticktock
Version: 0.1.2
Summary: adds least-recently-used cache management and automatic data timeout to Python's Shelf class.
Home-page: https://github.com/tsroten/ticktock
Author: Thomas Roten
Author-email: thomas@roten.us
License: UNKNOWN
Keywords: shelf,dictionary-like,dict-like,cache,lru,least-recently-used,timeout,persistent
Platform: any
Classifier: Programming Language :: Python
Classifier: Topic :: Software Development :: Libraries :: Python Modules
Classifier: Topic :: System :: Filesystems
Classifier: Topic :: Database :: Front-Ends
Classifier: License :: OSI Approved :: MIT License
Classifier: Operating System :: OS Independent
Classifier: Intended Audience :: Developers
Classifier: Development Status :: 4 - Beta
Classifier: Programming Language :: Python :: 2.6
Classifier: Programming Language :: Python :: 2.7
Classifier: Programming Language :: Python :: 3
